QUICKPLOT/__init__.py
QUICKPLOT/plot_utils.py
QPutils-0.0.3.dist-info/METADATA
QPutils-0.0.3.dist-info/WHEEL
QPutils-0.0.3.dist-info/top_level.txt
QPutils-0.0.3.dist-info/RECORD
